surropt/__init__.py
surropt/caballero/__init__.py
surropt/caballero/problem.py
surropt/core/__init__.py
surropt/core/nlp/__init__.py
surropt/core/options/__init__.py
surropt/core/options/nlp.py
surropt/core/procedures/__init__.py
surropt/core/procedures/output.py
surropt/core/utils/__init__.py
surropt/optimizers/__init__.py
surropt/optimizers/utils/__init__.py
surropt/utils/__init__.py
surropt/utils/matrixdivide.py
surropt/utils/models.py
surropt-0.0.12.dist-info/LICENSE
surropt-0.0.12.dist-info/WHEEL
surropt-0.0.12.dist-info/METADATA
surropt-0.0.12.dist-info/RECORD
