Metadata-Version: 2.1
Name: surropt
Version: 0.0.12
Summary: Surrogate optimization toolbox for time consuming models
Home-page: https://github.com/feslima/surropt
License: Apache-2.0
Author: Felipe Souza Lima
Author-email: feslima93@gmail.com
Requires-Python: >=3.5,<4.0
Classifier: License :: OSI Approved :: Apache Software License
Classifier: Operating System :: OS Independent
Classifier: Programming Language :: Python :: 3
Classifier: Programming Language :: Python :: 3.5
Classifier: Programming Language :: Python :: 3.6
Classifier: Programming Language :: Python :: 3.7
Classifier: Programming Language :: Python :: 3.8
Classifier: Programming Language :: Python :: 3.9
Classifier: Topic :: Scientific/Engineering
Requires-Dist: colorama (>=0.4.1,<0.5.0)
Requires-Dist: numpy (>=1.15.0,<2.0.0)
Requires-Dist: pydace (>=0.1.3,<0.2.0)
Requires-Dist: pydoe2 (>=1.2.1,<2.0.0)
Requires-Dist: requests (>=2.20.1,<3.0.0)
Requires-Dist: scipy (>=1.2.0,<2.0.0)
Project-URL: Repository, https://github.com/feslima/surropt
